pymcfost/CASA_simdata.py
pymcfost/SED.py
pymcfost/__init__.py
pymcfost/analytical2mcfost.py
pymcfost/disc_structure.py
pymcfost/dust.py
pymcfost/fargo2mcfost.py
pymcfost/image.py
pymcfost/line.py
pymcfost/parameters.py
pymcfost/pluto2mcfost.py
pymcfost/plutoTools.py
pymcfost/run.py
pymcfost/utils.py
pymcfost/wake.py
pymcfost/extinction_laws/kext_albedo_WD_MW_3.1_D03.all
pymcfost/extinction_laws/kext_albedo_WD_MW_4.0_D03.all
pymcfost/extinction_laws/kext_albedo_WD_MW_5.5_D03.all
pymcfost-0.1.1.dist-info/LICENSE
pymcfost-0.1.1.dist-info/METADATA
pymcfost-0.1.1.dist-info/WHEEL
pymcfost-0.1.1.dist-info/top_level.txt
pymcfost-0.1.1.dist-info/RECORD
