Metadata-Version: 2.1
Name: pymcfost
Version: 0.1.1
Summary: MCFOST post-processing in Python'
Author: Christophe Pinte
License: MIT
Project-URL: homepage, http://github.com/cpinte/pymcfost
Classifier: Programming Language :: Python :: 3
Classifier: Intended Audience :: Science/Research
Classifier: Topic :: Scientific/Engineering :: Astronomy
Classifier: Topic :: Scientific/Engineering :: Physics
Requires-Python: >=3.8
License-File: LICENSE
Requires-Dist: numpy
Requires-Dist: astropy
Requires-Dist: scipy
Requires-Dist: matplotlib
Requires-Dist: progressbar
Requires-Dist: cmasher
